voyger.py
voyger-0.7.dist-info/METADATA
voyger-0.7.dist-info/WHEEL
voyger-0.7.dist-info/top_level.txt
voyger-0.7.dist-info/RECORD
