Metadata-Version: 2.1
Name: voyger
Version: 0.7
Summary: A Python library for space exploration enthusiasts.
Author: Coataoc
Author-email: coataoccreater@gmail.com
